gbfs/__init__.py
gbfs/_version.py
gbfs/client.py
gbfs/const.py
gbfs/providers.py
gbfs/services.py
gbfs/data/__init__.py
gbfs/data/fetchers.py
gbfs/data/providers.py
gbfs/examples/__init__.py
gbfs/examples/basic_usage.py
gbfs/static/__init__.py
gbfs/static/systems.csv
gbfs/tests/__init__.py
gbfs/tests/test_client.py
gbfs/tests/test_integration.py
gbfs/tests/test_services.py
gbfs/tests/fixtures/__init__.py
gbfs_client-0.1.8.dist-info/LICENSE.txt
gbfs_client-0.1.8.dist-info/METADATA
gbfs_client-0.1.8.dist-info/WHEEL
gbfs_client-0.1.8.dist-info/top_level.txt
gbfs_client-0.1.8.dist-info/RECORD
