Metadata-Version: 2.1
Name: gbfs-client
Version: 0.1.8
Summary: Python client for discovering and capturing GBFS bikeshare feeds.
Home-page: https://github.com/jakehadar/gbfs-client
Author: Jake Hadar
Author-email: jake1025@gmail.com
License: UNKNOWN
Keywords: gbfs bikeshare client
Platform: UNKNOWN
Classifier: License :: OSI Approved :: MIT License
Classifier: Intended Audience :: Developers
Classifier: Natural Language :: English
Classifier: Programming Language :: Python
Requires-Python: >=2.7
Requires-Dist: requests
Requires-Dist: csv23
Requires-Dist: six
Provides-Extra: dev
Requires-Dist: tox ; extra == 'dev'
Requires-Dist: coverage ; extra == 'dev'
Requires-Dist: versioneer ; extra == 'dev'
Requires-Dist: twine ; extra == 'dev'
Requires-Dist: bumpversion ; extra == 'dev'
Provides-Extra: test
Requires-Dist: pytest ; extra == 'test'
Requires-Dist: coverage ; extra == 'test'
